hi_lasso_spark/Hi_LASSO_spark.py
hi_lasso_spark/__init__.py
hi_lasso_spark-1.0.0.dist-info/LICENSE
hi_lasso_spark-1.0.0.dist-info/METADATA
hi_lasso_spark-1.0.0.dist-info/WHEEL
hi_lasso_spark-1.0.0.dist-info/top_level.txt
hi_lasso_spark-1.0.0.dist-info/RECORD
