Metadata-Version: 2.1
Name: hi-lasso-spark
Version: 1.0.0
Summary: High-Demensional LASSO_spark
Home-page: https://github.com/datax-lab/Hi_Lasso_spark
Author: Seungha Jeong
Author-email: jsh29368602@gmail.com
License: UNKNOWN
Platform: UNKNOWN
Classifier: Programming Language :: Python :: 3
Classifier: License :: OSI Approved :: MIT License
Classifier: Operating System :: OS Independent
Requires-Python: >=3.6
License-File: LICENSE
Requires-Dist: glmnet
